tests/__init__.py
tests/test_password.py
tests/test_read_write.py
tinydb-encrypted-jsonstorage/__init__.py
tinydb-encrypted-jsonstorage/encrypted_json_storage.py
tinydb-encrypted-jsonstorage/tests/__init__.py
tinydb-encrypted-jsonstorage/tests/test_change_password.py
tinydb-encrypted-jsonstorage/tests/test_create.py
tinydb-encrypted-jsonstorage/tests/test_read.py
tinydb-encrypted-jsonstorage/tests/test_write.py
tinydb_encrypted_jsonstorage/__init__.py
tinydb_encrypted_jsonstorage/encrypted_json_storage.py
tinydb_encrypted_jsonstorage-0.1.2.dist-info/LICENSE
tinydb_encrypted_jsonstorage-0.1.2.dist-info/METADATA
tinydb_encrypted_jsonstorage-0.1.2.dist-info/WHEEL
tinydb_encrypted_jsonstorage-0.1.2.dist-info/top_level.txt
tinydb_encrypted_jsonstorage-0.1.2.dist-info/RECORD
