Metadata-Version: 2.1
Name: tinydb-encrypted-jsonstorage
Version: 0.1.2
Summary: A TinyDB storage implementation that uses JSON and encryption.
Home-page: https://github.com/stefanthaler/tinydb-encrypted-jsonstorage
Author: Stefan Thaler
Author-email: bruthaler@gmail.com
License: UNKNOWN
Platform: UNKNOWN
Classifier: Programming Language :: Python :: 3
Classifier: License :: OSI Approved :: MIT License
Classifier: Operating System :: OS Independent
Requires-Dist: pycryptodome
Requires-Dist: tinydb
